pyfpl/__init__.py
pyfpl/player.py
pyfpl/tempCodeRunnerFile.py
pyfpl/version.py
pyfpl-0.0.3.dist-info/LICENSE
pyfpl-0.0.3.dist-info/METADATA
pyfpl-0.0.3.dist-info/WHEEL
pyfpl-0.0.3.dist-info/top_level.txt
pyfpl-0.0.3.dist-info/RECORD
