Metadata-Version: 2.1
Name: pyfpl
Version: 0.0.3
Summary: FPL Analytics
Home-page: https://github.com/abhijith-git/pyfpl
Author: Abhijith Chandradas
Author-email: <abhijith.chandradas@gmail.com>
License: MIT
Keywords: python,football,fpl,data visualization,analytics
Platform: UNKNOWN
Classifier: Development Status :: 1 - Planning
Classifier: Intended Audience :: Developers
Classifier: License :: OSI Approved :: MIT License
Classifier: Natural Language :: English
Classifier: Operating System :: OS Independent
Classifier: Topic :: Scientific/Engineering :: Visualization
Classifier: Topic :: Scientific/Engineering :: Information Analysis
Classifier: Programming Language :: Python :: 3
Requires-Dist: matplotlib
Requires-Dist: pandas
Requires-Dist: numpy
Requires-Dist: seaborn
